vi_address/__init__.py
vi_address/admin.py
vi_address/apps.py
vi_address/models.py
vi_address/serializers.py
vi_address/tests.py
vi_address/urls.py
vi_address/views.py
vi_address/data/__init__.py
vi_address/data/tinh_tp.json
vi_address/data/quan-huyen/01.json
vi_address/data/quan-huyen/02.json
vi_address/data/quan-huyen/04.json
vi_address/data/quan-huyen/06.json
vi_address/data/quan-huyen/08.json
vi_address/data/quan-huyen/10.json
vi_address/data/quan-huyen/11.json
vi_address/data/quan-huyen/12.json
vi_address/data/quan-huyen/14.json
vi_address/data/quan-huyen/15.json
vi_address/data/quan-huyen/17.json
vi_address/data/quan-huyen/19.json
vi_address/data/quan-huyen/20.json
vi_address/data/quan-huyen/22.json
vi_address/data/quan-huyen/24.json
vi_address/data/quan-huyen/25.json
vi_address/data/quan-huyen/26.json
vi_address/data/quan-huyen/27.json
vi_address/data/quan-huyen/30.json
vi_address/data/quan-huyen/31.json
vi_address/data/quan-huyen/33.json
vi_address/data/quan-huyen/34.json
vi_address/data/quan-huyen/35.json
vi_address/data/quan-huyen/36.json
vi_address/data/quan-huyen/37.json
vi_address/data/quan-huyen/38.json
vi_address/data/quan-huyen/40.json
vi_address/data/quan-huyen/42.json
vi_address/data/quan-huyen/44.json
vi_address/data/quan-huyen/45.json
vi_address/data/quan-huyen/46.json
vi_address/data/quan-huyen/48.json
vi_address/data/quan-huyen/49.json
vi_address/data/quan-huyen/51.json
vi_address/data/quan-huyen/52.json
vi_address/data/quan-huyen/54.json
vi_address/data/quan-huyen/56.json
vi_address/data/quan-huyen/58.json
vi_address/data/quan-huyen/60.json
vi_address/data/quan-huyen/62.json
vi_address/data/quan-huyen/64.json
vi_address/data/quan-huyen/66.json
vi_address/data/quan-huyen/67.json
vi_address/data/quan-huyen/68.json
vi_address/data/quan-huyen/70.json
vi_address/data/quan-huyen/72.json
vi_address/data/quan-huyen/74.json
vi_address/data/quan-huyen/75.json
vi_address/data/quan-huyen/77.json
vi_address/data/quan-huyen/79.json
django_vi_address-0.1.6.dist-info/LICENSE
django_vi_address-0.1.6.dist-info/METADATA
django_vi_address-0.1.6.dist-info/WHEEL
django_vi_address-0.1.6.dist-info/top_level.txt
django_vi_address-0.1.6.dist-info/RECORD
